sqlitestorage/__init__.py
sqlitestorage/storage.py
sqlitestorage-1.1.1.dist-info/METADATA
sqlitestorage-1.1.1.dist-info/WHEEL
sqlitestorage-1.1.1.dist-info/top_level.txt
sqlitestorage-1.1.1.dist-info/RECORD
